<Module>
	<Name value="HeavyWeapons"/>
	<Id value="HeavyWeaponsCraft"/>
	<Version value="e1.9.0"/>
	<ModuleCategory value="Singleplayer"/>
	<DependedModules>
		<DependedModule Id="Native" DependentVersion="e1.9.0"/>
		<DependedModule Id="SandBoxCore" DependentVersion="e1.9.0"/>
		<DependedModule Id="Sandbox" DependentVersion="e1.9.0"/>
		<DependedModule Id="CustomBattle" DependentVersion="e1.9.0"/>
		<DependedModule Id ="StoryMode" DependentVersion="e1.9.0"/>
	</DependedModules>
	<Xmls>
		<XmlNode>
			<XmlName id="WeaponDescriptions" path="NewDescriptions"/>
			<IncludedGameTypes>
				<GameType value = "Campaign"/>
				<GameType value = "CampaignStoryMode"/>
				<GameType value = "CustomGame"/>
			</IncludedGameTypes>
		</XmlNode>
		<XmlNode>                
			<XmlName id="CraftingTemplates" path="HW_Templates"/>
			<IncludedGameTypes>
				<GameType value = "Campaign"/>
				<GameType value = "CampaignStoryMode"/>
				<GameType value = "CustomGame"/>
			</IncludedGameTypes>
		</XmlNode>   
		<XmlNode>                
			<XmlName id="GameText" path="ModuleStrings"/>
			<IncludedGameTypes>
				<GameType value = "Campaign"/>
				<GameType value = "CampaignStoryMode"/>
				<GameType value = "CustomGame"/>
			</IncludedGameTypes>
		</XmlNode>
	</Xmls>
</Module>
